.gitattributes
.gitignore
LICENSE
MANIFEST.in
README.md
setup.cfg
setup.py
docs/examples/examples.ipynb
docs/examples/data/mavg/0_random_walk.parquet
docs/examples/data/mavg/1_random_walk.parquet
docs/examples/data/mavg/2_random_walk.parquet
docs/examples/data/mavg/3_random_walk.parquet
docs/examples/data/mavg/4_random_walk.parquet
docs/examples/data/mavg/5_random_walk.parquet
docs/examples/data/mavg/6_random_walk.parquet
docs/examples/data/mavg/7_random_walk.parquet
docs/examples/data/mavg/8_random_walk.parquet
docs/examples/data/mavg/9_random_walk.parquet
docs/examples/data/pickle/random_walk.pkl.gz
docs/examples/data/raw/0_random_walk.parquet
docs/examples/data/raw/1_random_walk.parquet
docs/examples/data/raw/2_random_walk.parquet
docs/examples/data/raw/3_random_walk.parquet
docs/examples/data/raw/4_random_walk.parquet
docs/examples/data/raw/5_random_walk.parquet
docs/examples/data/raw/6_random_walk.parquet
docs/examples/data/raw/7_random_walk.parquet
docs/examples/data/raw/8_random_walk.parquet
docs/examples/data/raw/9_random_walk.parquet
oocas/__init__.py
oocas/cache.py
oocas/process.py
oocas/read.py
oocas/transform.py
oocas/write.py
oocas.egg-info/PKG-INFO
oocas.egg-info/SOURCES.txt
oocas.egg-info/dependency_links.txt
oocas.egg-info/requires.txt
oocas.egg-info/top_level.txt
tests/conftest.py
tests/test_cache.py
tests/test_process.py
tests/test_read.py
tests/test_transform.py
tests/test_write.py