Metadata-Version: 2.1
Name: oocas
Version: 1.0.1
Summary: Out-of-core data processing framework for pandas
Home-page: https://alvail.github.io/oocas
Author: Alex SIFEL
Author-email: alex.sifel@gmail.com
License: BSD
Platform: UNKNOWN
Classifier: License :: OSI Approved :: BSD License
Classifier: Programming Language :: Python
Classifier: Programming Language :: Python :: 3
Classifier: Programming Language :: Python :: 3 :: Only
Classifier: Topic :: Scientific/Engineering
Provides-Extra: dev
License-File: LICENSE
